payback_coupon_activator.py
payback_coupon_activator-0.0.3.dist-info/LICENSE.txt
payback_coupon_activator-0.0.3.dist-info/METADATA
payback_coupon_activator-0.0.3.dist-info/WHEEL
payback_coupon_activator-0.0.3.dist-info/entry_points.txt
payback_coupon_activator-0.0.3.dist-info/top_level.txt
payback_coupon_activator-0.0.3.dist-info/RECORD
