Metadata-Version: 2.1
Name: payback-coupon-activator
Version: 0.0.3
Summary: Activates all Payback coupons with Selenium WebDriver in Chrome logged into your Payback account.
Author-email: Robert Kampf <Robert.Kampf@gmx.de>
License: MIT License
Project-URL: Homepage, https://github.com/BobbyCephy/payback-coupon-activator
License-File: LICENSE.txt
Requires-Dist: selenium
